rambot/__init__.py
rambot/helpers.py
rambot/logging_config.py
rambot/browser/__init__.py
rambot/browser/driver.py
rambot/browser/element.py
rambot/database/__init__.py
rambot/database/models.py
rambot/database/sqlalchemy.py
rambot/http/__init__.py
rambot/http/exceptions.py
rambot/http/models.py
rambot/http/requests.py
rambot/http/utils.py
rambot/scraper/__init__.py
rambot/scraper/config.py
rambot/scraper/exception_handler.py
rambot/scraper/exceptions.py
rambot/scraper/html.py
rambot/scraper/models.py
rambot/scraper/scraper.py
rambot/scraper/utils.py
rambot/scraper/interceptor/__init__.py
rambot/scraper/interceptor/interceptor.py
rambot/scraper/interceptor/mitmproxy_interceptor.py
rambot/types/__init__.py
rambot/types/html.py
rambot/types/interceptor.py
rambot/types/request.py
rambot/types/scraper.py
rambot/webdriver/__init__.py
rambot/webdriver/driver.py
rambot/webdriver/tab.py
rambot/webdriver/core/__init__.py
rambot/webdriver/core/base.py
rambot/webdriver/core/util.py
rambot/webdriver/core/cdp/__init__.py
rambot/webdriver/core/cdp/network.py
rambot/webdriver/core/cdp/page.py
rambot/webdriver/core/cdp/runtime.py
rambot/webdriver/core/cdp/target.py
rambot/webdriver/core/cdp/util.py
rambot-0.1.6.dist-info/licenses/LICENSE
rambot-0.1.6.dist-info/METADATA
rambot-0.1.6.dist-info/WHEEL
rambot-0.1.6.dist-info/top_level.txt
rambot-0.1.6.dist-info/RECORD
