Metadata-Version: 2.4
Name: rambot
Version: 0.1.6
Summary: Configurable web scraping framework designed to automate data extraction from web pages
Author-email: Alexandre Vachon <alex.vachon@outlook.com>
License: MIT License
Project-URL: Source, https://github.com/AlexVachon/rambot
Classifier: Programming Language :: Python :: 3
Classifier: Operating System :: OS Independent
Classifier: License :: OSI Approved :: MIT License
Requires-Python: >=3.8
License-File: LICENSE
Requires-Dist: mitmproxy
Requires-Dist: botasaurus
Requires-Dist: botasaurus-driver
Requires-Dist: sqlalchemy
Requires-Dist: loguru
Requires-Dist: pydantic-settings
Requires-Dist: pydantic
Dynamic: license-file
